pagesign.py
pagesign-0.1.0.dist-info/LICENSE.txt
pagesign-0.1.0.dist-info/METADATA
pagesign-0.1.0.dist-info/WHEEL
pagesign-0.1.0.dist-info/top_level.txt
pagesign-0.1.0.dist-info/RECORD
