Metadata-Version: 2.1
Name: pagesign
Version: 0.1.0
Summary: A wrapper for the modern encryption and signing tools age and minisign
Home-page: https://docs.red-dove.com/pagesign/
Author: Vinay Sajip
Author-email: vinay_sajip@yahoo.co.uk
Maintainer: Vinay Sajip
Maintainer-email: vinay_sajip@yahoo.co.uk
License: Copyright (C) 2021 by Vinay Sajip. All Rights Reserved. See LICENSE.txt for license.
Download-URL: https://pypi.io/packages/source/p/pagesign/pagesign-0.1.0.tar.gz
Platform: No particular restrictions
Classifier: Development Status :: 3 - Alpha
Classifier: Intended Audience :: Developers
Classifier: License :: OSI Approved :: BSD License
Classifier: Programming Language :: Python
Classifier: Programming Language :: Python :: 3
Classifier: Programming Language :: Python :: 3.6
Classifier: Programming Language :: Python :: 3.7
Classifier: Programming Language :: Python :: 3.8
Classifier: Programming Language :: Python :: 3.9
Classifier: Operating System :: OS Independent
Classifier: Topic :: Software Development :: Libraries :: Python Modules
